yspycode/__init__.py
yspycode/decode.py
yspycode-1.0.0.dist-info/METADATA
yspycode-1.0.0.dist-info/WHEEL
yspycode-1.0.0.dist-info/top_level.txt
yspycode-1.0.0.dist-info/RECORD
