Metadata-Version: 2.1
Name: yspycode
Version: 1.0.0
Summary: My Code Decoder
Home-page: https://discord.gg/PDgPg5vdzJ
Author: Discord YS#0279
Author-email: ben23326326@gmail.com
License: MIT
Platform: UNKNOWN
Requires-Python: >=3.9
